cryptodataset/__init__.py
cryptodataset/base.py
cryptodataset/ccxt.py
cryptodataset/cli.py
cryptodataset/deribit.py
cryptodataset/max.py
cryptodataset/utils.py
cryptodataset-0.4.3.dist-info/LICENSE
cryptodataset-0.4.3.dist-info/METADATA
cryptodataset-0.4.3.dist-info/WHEEL
cryptodataset-0.4.3.dist-info/entry_points.txt
cryptodataset-0.4.3.dist-info/RECORD
